universaltag
