Metadata-Version: 1.0
Name: django-universaltag
Version: 0.1.7
Summary: Universal tagging library for Django
Home-page: https://github.com/lambdalisue/django-universaltag
Author: Alisue
Author-email: lambdalisue@hashnote.net
License: MIT
Download-URL: https://github.com/lambdalisue/django-universaltag/tarball/master
Keywords: django tagging universal tag
Platform: UNKNOWN
Classifier: Intended Audience :: Developers
Classifier: License :: OSI Approved :: MIT License
Classifier: Programming Language :: Python
Classifier: Topic :: Internet :: WWW/HTTP
